Workbook

Sheet Servicios
A1: Servicio | B1: Precio | C1: Costo insumos
A2: Corte dama | B2: 18000 | C2: 2500
A3: Corte caballero | B3: 12000 | C3: 1500
A4: Manicure | B4: 15000 | C4: 4000
A5: Cepillado | B5: 22000 | C5: 3500
A6: Color o mechas | B6: 55000 | C6: 20000
A7: Peinado para evento | B7: 40000 | C7: 7000

Sheet Agenda
A1: ID | B1: Fecha | C1: Día | D1: Servicio | E1: Cómo llegó | F1: Tipo | G1: Estado | H1: Precio | I1: Costo insumos | J1: Ingreso | K1: Costo cobrado | L1: Margen
A2: C01 | B2: 46251 | C2: Lunes | D2: Corte dama | E2: WhatsApp | F2: Ya venía | G2: Atendida | H2: 18000 | I2: 2500 | J2: =IF(G2="Atendida",H2,0) -> 18000 | K2: =IF(G2="Atendida",I2,0) -> 2500 | L2: =J2-K2 -> 15500
A3: C02 | B3: 46251 | C3: Lunes | D3: Corte caballero | E3: Llegó sin cita | F3: Nueva | G3: Atendida | H3: 12000 | I3: 1500 | J3: =IF(G3="Atendida",H3,0) -> 12000 | K3: =IF(G3="Atendida",I3,0) -> 1500 | L3: =J3-K3 -> 10500
A4: C03 | B4: 46251 | C4: Lunes | D4: Manicure | E4: WhatsApp | F4: Ya venía | G4: No llegó | H4: 15000 | I4: 4000 | J4: =IF(G4="Atendida",H4,0) -> 0 | K4: =IF(G4="Atendida",I4,0) -> 0 | L4: =J4-K4 -> 0
A5: C04 | B5: 46252 | C5: Martes | D5: Cepillado | E5: WhatsApp | F5: Nueva | G5: Atendida | H5: 22000 | I5: 3500 | J5: =IF(G5="Atendida",H5,0) -> 22000 | K5: =IF(G5="Atendida",I5,0) -> 3500 | L5: =J5-K5 -> 18500
A6: C05 | B6: 46252 | C6: Martes | D6: Corte caballero | E6: Llegó sin cita | F6: Nueva | G6: Atendida | H6: 12000 | I6: 1500 | J6: =IF(G6="Atendida",H6,0) -> 12000 | K6: =IF(G6="Atendida",I6,0) -> 1500 | L6: =J6-K6 -> 10500
A7: C06 | B7: 46253 | C7: Miércoles | D7: Color o mechas | E7: WhatsApp | F7: Ya venía | G7: Atendida | H7: 55000 | I7: 20000 | J7: =IF(G7="Atendida",H7,0) -> 55000 | K7: =IF(G7="Atendida",I7,0) -> 20000 | L7: =J7-K7 -> 35000
A8: C07 | B8: 46253 | C8: Miércoles | D8: Corte dama | E8: Vecina | F8: Nueva | G8: Atendida | H8: 18000 | I8: 2500 | J8: =IF(G8="Atendida",H8,0) -> 18000 | K8: =IF(G8="Atendida",I8,0) -> 2500 | L8: =J8-K8 -> 15500
A9: C08 | B9: 46253 | C9: Miércoles | D9: Corte caballero | E9: Llegó sin cita | F9: Nueva | G9: Atendida | H9: 12000 | I9: 1500 | J9: =IF(G9="Atendida",H9,0) -> 12000 | K9: =IF(G9="Atendida",I9,0) -> 1500 | L9: =J9-K9 -> 10500
A10: C09 | B10: 46253 | C10: Miércoles | D10: Manicure | E10: WhatsApp | F10: Ya venía | G10: Atendida | H10: 15000 | I10: 4000 | J10: =IF(G10="Atendida",H10,0) -> 15000 | K10: =IF(G10="Atendida",I10,0) -> 4000 | L10: =J10-K10 -> 11000
A11: C10 | B11: 46254 | C11: Jueves | D11: Peinado para evento | E11: WhatsApp | F11: Ya venía | G11: Atendida | H11: 40000 | I11: 7000 | J11: =IF(G11="Atendida",H11,0) -> 40000 | K11: =IF(G11="Atendida",I11,0) -> 7000 | L11: =J11-K11 -> 33000
A12: C11 | B12: 46254 | C12: Jueves | D12: Corte caballero | E12: Llegó sin cita | F12: Nueva | G12: Atendida | H12: 12000 | I12: 1500 | J12: =IF(G12="Atendida",H12,0) -> 12000 | K12: =IF(G12="Atendida",I12,0) -> 1500 | L12: =J12-K12 -> 10500
A13: C12 | B13: 46254 | C13: Jueves | D13: Corte dama | E13: WhatsApp | F13: Nueva | G13: No llegó | H13: 18000 | I13: 2500 | J13: =IF(G13="Atendida",H13,0) -> 0 | K13: =IF(G13="Atendida",I13,0) -> 0 | L13: =J13-K13 -> 0
... A41: C40 | B41: 46263 | C41: Sábado | D41: Cepillado | E41: WhatsApp | F41: Ya venía | G41: No llegó | H41: 22000 | I41: 3500 | J41: =IF(G41="Atendida",H41,0) -> 0 | K41: =IF(G41="Atendida",I41,0) -> 0 | L41: =J41-K41 -> 0

Sheet Indicadores
A1: Indicador | B1: Resultado
A2: Citas anotadas | B2: =COUNTA(Agenda!A2:A41) -> 40
A3: Atendidas | B3: =COUNTIF(Agenda!G2:G41,"Atendida") -> 35
A4: No llegaron | B4: =COUNTIF(Agenda!G2:G41,"No llegó") -> 5
A5: Ingreso | B5: =SUM(Agenda!J2:J41) -> 804000
A6: Costo de insumos usados | B6: =SUM(Agenda!K2:K41) -> 187000
A7: Margen antes de arriendo | B7: =SUM(Agenda!L2:L41) -> 617000
A8: Porcentaje de margen | B8: =IFERROR(B7/B5,0) -> 0.76741294
